[{"matchDate":"08-02-2025 22:01","matchType":"Trio Q.","winnerTeam":{"totalScore":484,"player1":{"pokemon":"gengar","battleItem":"xspeed","playerName":"Juquinha_@s","playerScore":28,"kills":3,"assists":3,"interrupts":0,"damageDone":27165,"damageTaken":64846,"damageHealed":14311,"abilities":["s21","s11"]},"player2":{"pokemon":"lucario","battleItem":"ejectbutton","playerName":"@AthJoestar","playerScore":241,"kills":8,"assists":4,"interrupts":0,"damageDone":59400,"damageTaken":46593,"damageHealed":20497,"abilities":["s11","u11"]},"player3":{"pokemon":"glaceon","battleItem":"ejectbutton","playerName":"PokeDarks","playerScore":11,"kills":8,"assists":9,"interrupts":3,"damageDone":102051,"damageTaken":42379,"damageHealed":17812,"abilities":["s11","s21"]},"player4":{"pokemon":"ceruledge","battleItem":"ejectbutton","playerName":"Passolargoツ","playerScore":24,"kills":4,"assists":5,"interrupts":1,"damageDone":33915,"damageTaken":71252,"damageHealed":10152,"abilities":["s12","s21"]},"player5":{"pokemon":"espeon","battleItem":"xspeed","playerName":"mazukiツ","playerScore":140,"kills":4,"assists":6,"interrupts":0,"damageDone":58487,"damageTaken":41940,"damageHealed":4647,"abilities":["s11","s22"]}},"defeatedTeam":{"totalScore":357,"player1":{"pokemon":"greninja","battleItem":"ejectbutton","playerName":"Feh26","playerScore":68,"kills":3,"assists":5,"interrupts":4,"damageDone":43103,"damageTaken":52448,"damageHealed":6086,"abilities":["s12","s22"]},"player2":{"pokemon":"sylveon","battleItem":"xspeed","playerName":"dorneus","playerScore":60,"kills":6,"assists":6,"interrupts":1,"damageDone":54735,"damageTaken":68179,"damageHealed":26185,"abilities":["s11","s21"]},"player3":{"pokemon":"psyduck","battleItem":"xspeed","playerName":"神・Navim^","playerScore":108,"kills":3,"assists":10,"interrupts":0,"damageDone":32868,"damageTaken":44581,"damageHealed":1459,"abilities":["s11","s22"]},"player4":{"pokemon":"urshifu","battleItem":"purify","playerName":"神・Deivid","playerScore":81,"kills":8,"assists":13,"interrupts":1,"damageDone":92900,"damageTaken":52895,"damageHealed":5369,"abilities":["s11","s21"]},"player5":{"pokemon":"blastoise","battleItem":"ejectbutton","playerName":"神・shad","playerScore":40,"kills":7,"assists":7,"interrupts":1,"damageDone":43404,"damageTaken":62915,"damageHealed":5582,"abilities":["s12","s21"]}}},{"matchDate":"08-02-2025 22:24","matchType":"Trio Q.","winnerTeam":{"totalScore":494,"player1":{"pokemon":"delphox","battleItem":"xspeed","playerName":"JhennosSloan","playerScore":40,"kills":5,"assists":7,"interrupts":3,"damageDone":39504,"damageTaken":48303,"damageHealed":6695,"abilities":["s11","s21"]},"player2":{"pokemon":"inteleon","battleItem":"ejectbutton","playerName":"Katyle","playerScore":72,"kills":1,"assists":6,"interrupts":1,"damageDone":64119,"damageTaken":37802,"damageHealed":8980,"abilities":["s11","s21"]},"player3":{"pokemon":"scizor","battleItem":"purify","playerName":"FL_ɑяɑмɑкɪ¿","playerScore":130,"kills":15,"assists":6,"interrupts":0,"damageDone":99224,"damageTaken":64659,"damageHealed":23592,"abilities":["scythers11","scythers22"]},"player4":{"pokemon":"blissey","battleItem":"xspeed","playerName":"DU・Maju","playerScore":180,"kills":2,"assists":13,"interrupts":0,"damageDone":8972,"damageTaken":79331,"damageHealed":135916,"abilities":["s11","s21"]},"player5":{"pokemon":"zeraora","battleItem":"purify","playerName":"DU・MatzzZ","playerScore":52,"kills":11,"assists":7,"interrupts":0,"damageDone":105226,"damageTaken":64222,"damageHealed":17401,"abilities":["s12","s22"]}},"defeatedTeam":{"totalScore":94,"player1":{"pokemon":"lucario","battleItem":"purify","playerName":"Cavalossauro","playerScore":41,"kills":3,"assists":6,"interrupts":0,"damageDone":89715,"damageTaken":81959,"damageHealed":18174,"abilities":["s12","u12"]},"player2":{"pokemon":"decidueye","battleItem":"ejectbutton","playerName":"äḳïṛä","playerScore":0,"kills":6,"assists":2,"interrupts":0,"damageDone":59386,"damageTaken":43420,"damageHealed":4292,"abilities":["s12","s22"]},"player3":{"pokemon":"psyduck","battleItem":"xspeed","playerName":"神・Navim^","playerScore":0,"kills":2,"assists":6,"interrupts":0,"damageDone":43768,"damageTaken":57408,"damageHealed":0,"abilities":["s11","s22"]},"player4":{"pokemon":"urshifu","battleItem":"ejectbutton","playerName":"神・Deivid","playerScore":0,"kills":2,"assists":5,"interrupts":0,"damageDone":61906,"damageTaken":78103,"damageHealed":2703,"abilities":["s11","s21"]},"player5":{"pokemon":"blastoise","battleItem":"ejectbutton","playerName":"神・shad","playerScore":53,"kills":2,"assists":2,"interrupts":0,"damageDone":39542,"damageTaken":56155,"damageHealed":366,"abilities":["s12","s21"]}}},{"matchDate":"09-02-2025 21:22","matchType":"Trio Q.","winnerTeam":{"totalScore":271,"player1":{"pokemon":"sylveon","battleItem":"xspeed","playerName":"Don・Iván","playerScore":30,"kills":8,"assists":12,"interrupts":1,"damageDone":48014,"damageTaken":38300,"damageHealed":20275,"abilities":["s11","s21"]},"player2":{"pokemon":"zeraora","battleItem":"xattack","playerName":"Chispan't?","playerScore":19,"kills":5,"assists":8,"interrupts":0,"damageDone":68218,"damageTaken":36044,"damageHealed":7626,"abilities":["s12","s22"]},"player3":{"pokemon":"psyduck","battleItem":"xspeed","playerName":"神・Navim^","playerScore":59,"kills":7,"assists":16,"interrupts":0,"damageDone":30088,"damageTaken":20677,"damageHealed":8875,"abilities":["s11","s21"]},"player4":{"pokemon":"blastoise","battleItem":"ejectbutton","playerName":"神・shad","playerScore":59,"kills":2,"assists":21,"interrupts":0,"damageDone":50215,"damageTaken":15028,"damageHealed":3997,"abilities":["s12","s21"]},"player5":{"pokemon":"mimikyu","battleItem":"purify","playerName":"神・Deivid","playerScore":104,"kills":10,"assists":12,"interrupts":0,"damageDone":60856,"damageTaken":17082,"damageHealed":16059,"abilities":["s12","s21"]}},"defeatedTeam":{"totalScore":167,"player1":{"pokemon":"glaceon","battleItem":"xspeed","playerName":"NINㆍZelda","playerScore":52,"kills":1,"assists":3,"interrupts":0,"damageDone":35191,"damageTaken":45107,"damageHealed":8279,"abilities":["s11","s21"]},"player2":{"pokemon":"umbreon","battleItem":"ejectbutton","playerName":"HyruleZora","playerScore":13,"kills":2,"assists":2,"interrupts":0,"damageDone":11700,"damageTaken":57917,"damageHealed":25181,"abilities":["s11","s21"]},"player3":{"pokemon":"zacian","battleItem":"xspeed","playerName":"THC-KENPACHI","playerScore":32,"kills":4,"assists":3,"interrupts":0,"damageDone":33266,"damageTaken":57613,"damageHealed":5189,"abilities":["s11","s22"]},"player4":{"pokemon":"comfey","battleItem":"gear","playerName":"天Gouki","playerScore":12,"kills":0,"assists":6,"interrupts":0,"damageDone":4869,"damageTaken":34874,"damageHealed":22577,"abilities":["s11","s211"]},"player5":{"pokemon":"urshifu","battleItem":"xattack","playerName":"THC-Fuimpa","playerScore":38,"kills":3,"assists":3,"interrupts":0,"damageDone":42105,"damageTaken":61880,"damageHealed":7797,"abilities":["s12","s22"]}}},{"matchDate":"09-02-2025 21:37","matchType":"Trio Q.","winnerTeam":{"totalScore":190,"player1":{"pokemon":"ninetales","battleItem":"xspeed","playerName":"LáFantasia","playerScore":45,"kills":9,"assists":10,"interrupts":1,"damageDone":86967,"damageTaken":44058,"damageHealed":13602,"abilities":["s12","s22"]},"player2":{"pokemon":"wigglytuff","battleItem":"ejectbutton","playerName":"LáMirage","playerScore":43,"kills":4,"assists":16,"interrupts":1,"damageDone":27422,"damageTaken":42306,"damageHealed":6276,"abilities":["s12","s22"]},"player3":{"pokemon":"blastoise","battleItem":"ejectbutton","playerName":"神・shad","playerScore":52,"kills":4,"assists":14,"interrupts":0,"damageDone":49115,"damageTaken":34728,"damageHealed":7437,"abilities":["s12","s21"]},"player4":{"pokemon":"psyduck","battleItem":"xspeed","playerName":"神・Navim^","playerScore":0,"kills":1,"assists":8,"interrupts":1,"damageDone":24801,"damageTaken":39501,"damageHealed":1540,"abilities":["s11","s22"]},"player5":{"pokemon":"ceruledge","battleItem":"purify","playerName":"神・Deivid","playerScore":50,"kills":11,"assists":5,"interrupts":2,"damageDone":77745,"damageTaken":33799,"damageHealed":10193,"abilities":["s12","s21"]}},"defeatedTeam":{"totalScore":209,"player1":{"pokemon":"venusaur","battleItem":"potion","playerName":"太陽的","playerScore":4,"kills":1,"assists":7,"interrupts":2,"damageDone":35808,"damageTaken":66166,"damageHealed":16570,"abilities":["s12","u12"]},"player2":{"pokemon":"scizor","battleItem":"purify","playerName":"月球小行星","playerScore":52,"kills":4,"assists":2,"interrupts":1,"damageDone":43010,"damageTaken":56795,"damageHealed":13925,"abilities":["scythers11","scythers21"]},"player3":{"pokemon":"zoroark","battleItem":"purify","playerName":"Blessed神","playerScore":77,"kills":8,"assists":5,"interrupts":2,"damageDone":64553,"damageTaken":65903,"damageHealed":1696,"abilities":["s11","s22"]},"player4":{"pokemon":"comfey","battleItem":"gear","playerName":"lukezin冥","playerScore":23,"kills":2,"assists":13,"interrupts":2,"damageDone":11727,"damageTaken":21194,"damageHealed":62386,"abilities":["s11","s211"]},"player5":{"pokemon":"darkrai","battleItem":"purify","playerName":"REVERSO@NBA","playerScore":53,"kills":3,"assists":4,"interrupts":1,"damageDone":39294,"damageTaken":55992,"damageHealed":1759,"abilities":["s11","s12"]}}},{"matchDate":"09-02-2025 21:53","matchType":"Trio Q.","winnerTeam":{"totalScore":405,"player1":{"pokemon":"mrmime","battleItem":"xspeed","playerName":"花・Nameless","playerScore":112,"kills":3,"assists":10,"interrupts":1,"damageDone":35425,"damageTaken":37502,"damageHealed":1293,"abilities":["s21","s11"]},"player2":{"pokemon":"mewtwoy","battleItem":"xattack","playerName":"HeхZ愛","playerScore":28,"kills":6,"assists":9,"interrupts":0,"damageDone":71959,"damageTaken":22163,"damageHealed":8050,"abilities":["s12","s221"]},"player3":{"pokemon":"miraidon","battleItem":"ejectbutton","playerName":"GS・Tonyttor","playerScore":72,"kills":5,"assists":9,"interrupts":1,"damageDone":63130,"damageTaken":34683,"damageHealed":0,"abilities":["s11","s21"]},"player4":{"pokemon":"hoopa","battleItem":"ejectbutton","playerName":"ACE・Leø","playerScore":114,"kills":4,"assists":15,"interrupts":0,"damageDone":34156,"damageTaken":59323,"damageHealed":3944,"abilities":["s11","s21"]},"player5":{"pokemon":"urshifu","battleItem":"ejectbutton","playerName":"GS・Pim","playerScore":79,"kills":9,"assists":7,"interrupts":0,"damageDone":57988,"damageTaken":59969,"damageHealed":3648,"abilities":["s11","s21"]}},"defeatedTeam":{"totalScore":385,"player1":{"pokemon":"scizor","battleItem":"purify","playerName":"nigнтмaяєѕ","playerScore":104,"kills":5,"assists":2,"interrupts":0,"damageDone":43979,"damageTaken":38446,"damageHealed":6139,"abilities":["scythers111","scythers22"]},"player2":{"pokemon":"pikachu","battleItem":"ejectbutton","playerName":"flad","playerScore":0,"kills":5,"assists":3,"interrupts":6,"damageDone":58071,"damageTaken":65039,"damageHealed":4359,"abilities":["u11","u12"]},"player3":{"pokemon":"blastoise","battleItem":"ejectbutton","playerName":"神・shad","playerScore":130,"kills":1,"assists":2,"interrupts":0,"damageDone":20848,"damageTaken":49029,"damageHealed":3492,"abilities":["s12","s21"]},"player4":{"pokemon":"blissey","battleItem":"xspeed","playerName":"神・Navim^","playerScore":71,"kills":0,"assists":5,"interrupts":1,"damageDone":24905,"damageTaken":54544,"damageHealed":45144,"abilities":["s11","s21"]},"player5":{"pokemon":"mimikyu","battleItem":"purify","playerName":"神・Deivid","playerScore":40,"kills":6,"assists":5,"interrupts":2,"damageDone":65837,"damageTaken":55600,"damageHealed":12591,"abilities":["s12","s21"]}}},{"matchDate":"09-02-2025 22:08","matchType":"Trio Q.","winnerTeam":{"totalScore":724,"player1":{"pokemon":"pikachu","battleItem":"xspeed","playerName":"JaquePatomba","playerScore":113,"kills":8,"assists":7,"interrupts":0,"damageDone":69918,"damageTaken":51527,"damageHealed":13695,"abilities":["s12","u12"]},"player2":{"pokemon":"armarouge","battleItem":"xspeed","playerName":"alaskmoon","playerScore":170,"kills":4,"assists":3,"interrupts":5,"damageDone":43001,"damageTaken":36482,"damageHealed":6215,"abilities":["s11","s22"]},"player3":{"pokemon":"comfey","battleItem":"gear","playerName":"7P.Sophia","playerScore":126,"kills":2,"assists":16,"interrupts":1,"damageDone":27433,"damageTaken":18023,"damageHealed":56312,"abilities":["s11","s211"]},"player4":{"pokemon":"gardevoir","battleItem":"xspeed","playerName":"・Gaiel・","playerScore":140,"kills":5,"assists":8,"interrupts":0,"damageDone":67553,"damageTaken":42612,"damageHealed":916,"abilities":["s12","s21"]},"player5":{"pokemon":"tinkaton","battleItem":"ejectbutton","playerName":"BOOM_COACH","playerScore":175,"kills":9,"assists":9,"interrupts":0,"damageDone":104300,"damageTaken":114190,"damageHealed":31875,"abilities":["s11","s22"]}},"defeatedTeam":{"totalScore":280,"player1":{"pokemon":"decidueye","battleItem":"xspeed","playerName":"PapaiCrustle","playerScore":30,"kills":4,"assists":8,"interrupts":1,"damageDone":60165,"damageTaken":39750,"damageHealed":6336,"abilities":["s12","s21"]},"player2":{"pokemon":"mewtwox","battleItem":"potion","playerName":"ST_THELIK","playerScore":33,"kills":4,"assists":2,"interrupts":1,"damageDone":48359,"damageTaken":73674,"damageHealed":16073,"abilities":["s11","s21"]},"player3":{"pokemon":"blastoise","battleItem":"ejectbutton","playerName":"神・shad","playerScore":58,"kills":4,"assists":9,"interrupts":0,"damageDone":47023,"damageTaken":62502,"damageHealed":8472,"abilities":["s12","s21"]},"player4":{"pokemon":"psyduck","battleItem":"xspeed","playerName":"神・Navim^","playerScore":41,"kills":0,"assists":9,"interrupts":0,"damageDone":26698,"damageTaken":65646,"damageHealed":14787,"abilities":["s11","s22"]},"player5":{"pokemon":"urshifu","battleItem":"purify","playerName":"神・Deivid","playerScore":78,"kills":10,"assists":6,"interrupts":1,"damageDone":80589,"damageTaken":70633,"damageHealed":22295,"abilities":["s12","s22"]}}}]