[{"matchDate":"24-06-2025 15:37","matchType":"Duo Q.","winnerTeam":{"totalScore":893,"player1":{"pokemon":"goodra","battleItem":"potion","playerName":"RNT-Anderson","playerScore":218,"kills":3,"assists":10,"interrupts":0,"damageDone":35971,"damageTaken":82470,"damageHealed":43913,"abilities":["s12","s22"]},"player2":{"pokemon":"hoopa","battleItem":"xspeed","playerName":"M1・sleep","playerScore":120,"kills":3,"assists":16,"interrupts":4,"damageDone":47766,"damageTaken":65880,"damageHealed":5114,"abilities":["s11","s21"]},"player3":{"pokemon":"metagross","battleItem":"potion","playerName":"Merumey","playerScore":260,"kills":8,"assists":10,"interrupts":0,"damageDone":74087,"damageTaken":56288,"damageHealed":32902,"abilities":["s11","s22"]},"player4":{"pokemon":"cinderace","battleItem":"ejectbutton","playerName":"_.Erick","playerScore":166,"kills":10,"assists":9,"interrupts":0,"damageDone":71177,"damageTaken":47891,"damageHealed":11146,"abilities":["s12","s22"]},"player5":{"pokemon":"talonflame","battleItem":"shedinjadoll","playerName":"Perchansey","playerScore":109,"kills":12,"assists":5,"interrupts":0,"damageDone":70203,"damageTaken":41481,"damageHealed":4219,"abilities":["s12","s21"]}},"defeatedTeam":{"totalScore":277,"player1":{"pokemon":"mimikyu","battleItem":"xattack","playerName":"Hipacia","playerScore":162,"kills":1,"assists":1,"interrupts":2,"damageDone":25734,"damageTaken":41105,"damageHealed":6375,"abilities":["s11","s21"]},"player2":{"pokemon":"gardevoir","battleItem":"ejectbutton","playerName":"GRN・Leone","playerScore":0,"kills":1,"assists":5,"interrupts":2,"damageDone":39114,"damageTaken":40800,"damageHealed":3075,"abilities":["s12","s22"]},"player3":{"pokemon":"rapidash","battleItem":"potion","playerName":"GRN・Dɾacoツ","playerScore":46,"kills":5,"assists":4,"interrupts":1,"damageDone":63565,"damageTaken":63867,"damageHealed":13731,"abilities":["s11","s22"]},"player4":{"pokemon":"azumarill","battleItem":"xspeed","playerName":"RkT・Joker","playerScore":40,"kills":6,"assists":4,"interrupts":0,"damageDone":75789,"damageTaken":100273,"damageHealed":37978,"abilities":["s11","s21"]},"player5":{"pokemon":"pikachu","battleItem":"xattack","playerName":"MedC137","playerScore":29,"kills":3,"assists":10,"interrupts":7,"damageDone":89808,"damageTaken":53159,"damageHealed":12516,"abilities":["u11","u12"]}}},{"matchDate":"24-06-2025 15:49","matchType":"Duo Q.","winnerTeam":{"totalScore":1054,"player1":{"pokemon":"metagross","battleItem":"xspeed","playerName":"VenexoSon","playerScore":232,"kills":13,"assists":6,"interrupts":0,"damageDone":71712,"damageTaken":54203,"damageHealed":20827,"abilities":["s11","s22"]},"player2":{"pokemon":"hoopa","battleItem":"ejectbutton","playerName":"ㅼPunk","playerScore":104,"kills":2,"assists":8,"interrupts":10,"damageDone":27851,"damageTaken":45285,"damageHealed":1028,"abilities":["s11","s22"]},"player3":{"pokemon":"meowscara","battleItem":"shedinjadoll","playerName":"FULERAGE","playerScore":186,"kills":10,"assists":4,"interrupts":1,"damageDone":86041,"damageTaken":49274,"damageHealed":5452,"abilities":["s11","s22"]},"player4":{"pokemon":"azumarill","battleItem":"xattack","playerName":"Cotias","playerScore":210,"kills":5,"assists":18,"interrupts":0,"damageDone":105831,"damageTaken":73415,"damageHealed":35271,"abilities":["s11","s21"]},"player5":{"pokemon":"espeon","battleItem":"xspeed","playerName":"psv_sgl","playerScore":302,"kills":5,"assists":14,"interrupts":0,"damageDone":66869,"damageTaken":40066,"damageHealed":8231,"abilities":["s12","s21"]}},"defeatedTeam":{"totalScore":224,"player1":{"pokemon":"dragonite","battleItem":"purify","playerName":"Fly_skill","playerScore":117,"kills":2,"assists":2,"interrupts":0,"damageDone":45629,"damageTaken":66464,"damageHealed":8993,"abilities":["s12","s22"]},"player2":{"pokemon":"slowbro","battleItem":"potion","playerName":"の.Hellen.の","playerScore":30,"kills":2,"assists":8,"interrupts":0,"damageDone":47814,"damageTaken":111713,"damageHealed":57312,"abilities":["s12","s21"]},"player3":{"pokemon":"tsareena","battleItem":"purify","playerName":"影-Belion!","playerScore":6,"kills":6,"assists":6,"interrupts":1,"damageDone":50306,"damageTaken":63478,"damageHealed":25334,"abilities":["s11","s21"]},"player4":{"pokemon":"chandelure","battleItem":"ejectbutton","playerName":"GRN・Leone","playerScore":14,"kills":7,"assists":9,"interrupts":5,"damageDone":59886,"damageTaken":44427,"damageHealed":9086,"abilities":["s12","s22"]},"player5":{"pokemon":"rapidash","battleItem":"potion","playerName":"GRN・Dɾacoツ","playerScore":57,"kills":6,"assists":9,"interrupts":1,"damageDone":58608,"damageTaken":72222,"damageHealed":14642,"abilities":["s11","s22"]}}},{"matchDate":"24-06-2025 16:02","matchType":"Duo Q.","winnerTeam":{"totalScore":521,"player1":{"pokemon":"zeraora","battleItem":"xattack","playerName":"^_^BRABOX^_^","playerScore":255,"kills":8,"assists":1,"interrupts":0,"damageDone":66174,"damageTaken":27984,"damageHealed":3361,"abilities":["s12","s22"]},"player2":{"pokemon":"pikachu","battleItem":"purify","playerName":"DeigO","playerScore":61,"kills":4,"assists":2,"interrupts":2,"damageDone":31831,"damageTaken":37657,"damageHealed":3477,"abilities":["u11","u12"]},"player3":{"pokemon":"tsareena","battleItem":"purify","playerName":"影-Belion!","playerScore":155,"kills":9,"assists":4,"interrupts":2,"damageDone":76985,"damageTaken":49545,"damageHealed":21498,"abilities":["s11","s21"]},"player4":{"pokemon":"blaziken","battleItem":"ejectbutton","playerName":"DUT・Guará","playerScore":33,"kills":3,"assists":4,"interrupts":0,"damageDone":39902,"damageTaken":45797,"damageHealed":7907,"abilities":["s12","s22"]},"player5":{"pokemon":"snorlax","battleItem":"ejectbutton","playerName":"DUT・Capita","playerScore":17,"kills":0,"assists":5,"interrupts":0,"damageDone":15658,"damageTaken":73944,"damageHealed":7363,"abilities":["s12","s22"]}},"defeatedTeam":{"totalScore":491,"player1":{"pokemon":"goodra","battleItem":"potion","playerName":"Venusianme86","playerScore":0,"kills":1,"assists":5,"interrupts":1,"damageDone":39808,"damageTaken":70025,"damageHealed":39982,"abilities":["s12","s22"]},"player2":{"pokemon":"pikachu","battleItem":"ejectbutton","playerName":"Dredd_J","playerScore":56,"kills":6,"assists":9,"interrupts":0,"damageDone":57690,"damageTaken":45073,"damageHealed":6177,"abilities":["s12","u12"]},"player3":{"pokemon":"talonflame","battleItem":"ganrao","playerName":"WMA・RICK","playerScore":141,"kills":6,"assists":5,"interrupts":4,"damageDone":51584,"damageTaken":48186,"damageHealed":5330,"abilities":["s12","s21"]},"player4":{"pokemon":"dragapult","battleItem":"ejectbutton","playerName":"GRN・Leone","playerScore":20,"kills":2,"assists":11,"interrupts":3,"damageDone":36588,"damageTaken":20764,"damageHealed":4637,"abilities":["s11","s212"]},"player5":{"pokemon":"rapidash","battleItem":"ganrao","playerName":"GRN・Dɾacoツ","playerScore":224,"kills":7,"assists":7,"interrupts":0,"damageDone":49257,"damageTaken":46502,"damageHealed":14114,"abilities":["s11","s22"]}}}]