[{"matchDate":"18-06-2025 01:13","matchType":"Solo Q.","winnerTeam":{"totalScore":661,"player1":{"pokemon":"glaceon","battleItem":"xspeed","playerName":"Evigheden","playerScore":23,"kills":1,"assists":5,"interrupts":0,"damageDone":41111,"damageTaken":40918,"damageHealed":16760,"abilities":["s11","s21"]},"player2":{"pokemon":"cinderace","battleItem":"xspeed","playerName":"Mond15","playerScore":140,"kills":3,"assists":4,"interrupts":2,"damageDone":47082,"damageTaken":39630,"damageHealed":8086,"abilities":["s11","s21"]},"player3":{"pokemon":"snorlax","battleItem":"xspeed","playerName":"!I_AM_M4ST3R","playerScore":330,"kills":6,"assists":7,"interrupts":0,"damageDone":71013,"damageTaken":78650,"damageHealed":43380,"abilities":["s11","s2"]},"player4":{"pokemon":"mimikyu","battleItem":"ejectbutton","playerName":"MapleBonsai","playerScore":138,"kills":10,"assists":6,"interrupts":1,"damageDone":79754,"damageTaken":58132,"damageHealed":13142,"abilities":["s11","s21"]},"player5":{"pokemon":"decidueye","battleItem":"ejectbutton","playerName":"Xyphyrion","playerScore":30,"kills":6,"assists":6,"interrupts":0,"damageDone":86156,"damageTaken":28447,"damageHealed":3465,"abilities":["s12","s22"]}},"defeatedTeam":{"totalScore":105,"player1":{"pokemon":"inteleon","battleItem":"ejectbutton","playerName":"GRN・Leone","playerScore":0,"kills":2,"assists":5,"interrupts":1,"damageDone":43194,"damageTaken":36234,"damageHealed":4775,"abilities":["s11","s21"]},"player2":{"pokemon":"greninja","battleItem":"xspeed","playerName":"Akira167","playerScore":0,"kills":18,"assists":2,"interrupts":0,"damageDone":109278,"damageTaken":76197,"damageHealed":16199,"abilities":["s11","s21"]},"player3":{"pokemon":"umbreon","battleItem":"potion","playerName":"yJikGy_","playerScore":100,"kills":0,"assists":7,"interrupts":0,"damageDone":16290,"damageTaken":94649,"damageHealed":49312,"abilities":["s12","s21"]},"player4":{"pokemon":"venusaur","battleItem":"ejectbutton","playerName":"Louiszin","playerScore":5,"kills":1,"assists":7,"interrupts":6,"damageDone":59011,"damageTaken":75766,"damageHealed":5708,"abilities":["s11","u11"]},"player5":{"pokemon":"comfey","battleItem":"gear","playerName":"NICKE","playerScore":0,"kills":1,"assists":12,"interrupts":3,"damageDone":18004,"damageTaken":42270,"damageHealed":44478,"abilities":["s11","s211"]}}},{"matchDate":"18-06-2025 09:10","matchType":"Solo Q.","winnerTeam":{"totalScore":498,"player1":{"pokemon":"hooh","battleItem":"xspeed","playerName":"Majin*","playerScore":166,"kills":2,"assists":6,"interrupts":0,"damageDone":28298,"damageTaken":54238,"damageHealed":36536,"abilities":["s11","s21"]},"player2":{"pokemon":"greninja","battleItem":"ejectbutton","playerName":"Markes92","playerScore":38,"kills":6,"assists":4,"interrupts":1,"damageDone":39477,"damageTaken":41569,"damageHealed":10474,"abilities":["s12","s21"]},"player3":{"pokemon":"ninetales","battleItem":"ejectbutton","playerName":"Player103473","playerScore":116,"kills":3,"assists":7,"interrupts":0,"damageDone":46734,"damageTaken":49085,"damageHealed":677,"abilities":["s11","s21"]},"player4":{"pokemon":"darkrai","battleItem":"purify","playerName":"LD・Luisin","playerScore":20,"kills":10,"assists":3,"interrupts":0,"damageDone":66515,"damageTaken":47287,"damageHealed":3245,"abilities":["s11","s12"]},"player5":{"pokemon":"sylveon","battleItem":"potion","playerName":"DO・Oskitar","playerScore":158,"kills":12,"assists":8,"interrupts":0,"damageDone":110932,"damageTaken":102610,"damageHealed":61425,"abilities":["s11","s21"]}},"defeatedTeam":{"totalScore":352,"player1":{"pokemon":"inteleon","battleItem":"ejectbutton","playerName":"GRN・Leone","playerScore":82,"kills":6,"assists":5,"interrupts":0,"damageDone":53654,"damageTaken":42806,"damageHealed":9654,"abilities":["s11","s21"]},"player2":{"pokemon":"gengar","battleItem":"ejectbutton","playerName":"Bad_jungler","playerScore":37,"kills":5,"assists":5,"interrupts":0,"damageDone":44433,"damageTaken":51648,"damageHealed":14230,"abilities":["s21","s11"]},"player3":{"pokemon":"tsareena","battleItem":"xattack","playerName":"guardian102","playerScore":96,"kills":7,"assists":5,"interrupts":1,"damageDone":72082,"damageTaken":69241,"damageHealed":12448,"abilities":["s12","s21"]},"player4":{"pokemon":"chandelure","battleItem":"ejectbutton","playerName":"BEBECIÖ","playerScore":53,"kills":12,"assists":13,"interrupts":0,"damageDone":96665,"damageTaken":51109,"damageHealed":13444,"abilities":["s120","s22"]},"player5":{"pokemon":"trevenant","battleItem":"xspeed","playerName":"Agrupémonos","playerScore":48,"kills":2,"assists":4,"interrupts":0,"damageDone":27955,"damageTaken":77152,"damageHealed":25719,"abilities":["s12","s21"]}}},{"matchDate":"18-06-2025 09:23","matchType":"Solo Q.","winnerTeam":{"totalScore":379,"player1":{"pokemon":"snorlax","battleItem":"potion","playerName":"国王Lux","playerScore":73,"kills":6,"assists":9,"interrupts":0,"damageDone":46414,"damageTaken":62879,"damageHealed":29412,"abilities":["s11","s22"]},"player2":{"pokemon":"ninetales","battleItem":"ejectbutton","playerName":"Silvalves","playerScore":17,"kills":1,"assists":10,"interrupts":0,"damageDone":50960,"damageTaken":42635,"damageHealed":0,"abilities":["s11","s21"]},"player3":{"pokemon":"sableye","battleItem":"xspeed","playerName":"BaelonII","playerScore":111,"kills":2,"assists":6,"interrupts":2,"damageDone":16791,"damageTaken":17663,"damageHealed":1409,"abilities":["s11","s21"]},"player4":{"pokemon":"inteleon","battleItem":"ejectbutton","playerName":"GRN・Leone","playerScore":30,"kills":3,"assists":0,"interrupts":0,"damageDone":20367,"damageTaken":22619,"damageHealed":5014,"abilities":["s11","s21"]},"player5":{"pokemon":"buzzwole","battleItem":"ejectbutton","playerName":"Charles_Zard","playerScore":128,"kills":20,"assists":3,"interrupts":0,"damageDone":108245,"damageTaken":50765,"damageHealed":23410,"abilities":["s12","s22"]}},"defeatedTeam":{"totalScore":137,"player1":{"pokemon":"decidueye","battleItem":"potion","playerName":"@JadsonMarin","playerScore":0,"kills":1,"assists":2,"interrupts":0,"damageDone":35298,"damageTaken":45124,"damageHealed":6907,"abilities":["s12","s22"]},"player2":{"pokemon":"scizor","battleItem":"potion","playerName":"PROFESSOR_RJ","playerScore":19,"kills":5,"assists":0,"interrupts":1,"damageDone":55215,"damageTaken":65860,"damageHealed":26337,"abilities":["scythers121","s22"]},"player3":{"pokemon":"mimikyu","battleItem":"potion","playerName":"Toroti","playerScore":16,"kills":7,"assists":2,"interrupts":0,"damageDone":49396,"damageTaken":45047,"damageHealed":16757,"abilities":["s11","s21"]},"player4":{"pokemon":"blastoise","battleItem":"ejectbutton","playerName":"PDX・Munn-ra","playerScore":72,"kills":2,"assists":3,"interrupts":0,"damageDone":22133,"damageTaken":44681,"damageHealed":1223,"abilities":["s11","s22"]},"player5":{"pokemon":"ninetales","battleItem":"xattack","playerName":"digimaru","playerScore":30,"kills":0,"assists":3,"interrupts":1,"damageDone":34519,"damageTaken":42065,"damageHealed":2061,"abilities":["s11","s21"]}}},{"matchDate":"18-06-2025 09:35","matchType":"Solo Q.","winnerTeam":{"totalScore":222,"player1":{"pokemon":"glaceon","battleItem":"xattack","playerName":"tenebroso","playerScore":74,"kills":7,"assists":7,"interrupts":3,"damageDone":55109,"damageTaken":38163,"damageHealed":9007,"abilities":["s11","s21"]},"player2":{"pokemon":"gengar","battleItem":"ejectbutton","playerName":"slash_acs","playerScore":13,"kills":7,"assists":9,"interrupts":0,"damageDone":74549,"damageTaken":62323,"damageHealed":22519,"abilities":["s21","s11"]},"player3":{"pokemon":"buzzwole","battleItem":"ejectbutton","playerName":"Charles_Zard","playerScore":53,"kills":1,"assists":6,"interrupts":1,"damageDone":51670,"damageTaken":66993,"damageHealed":9831,"abilities":["s12","s22"]},"player4":{"pokemon":"blissey","battleItem":"xspeed","playerName":"SSJ×Wailord","playerScore":28,"kills":1,"assists":10,"interrupts":3,"damageDone":9825,"damageTaken":46302,"damageHealed":5946,"abilities":["s12","s22"]},"player5":{"pokemon":"mewtwoy","battleItem":"xattack","playerName":"SSJ×Skitty","playerScore":14,"kills":12,"assists":6,"interrupts":2,"damageDone":93126,"damageTaken":39628,"damageHealed":8132,"abilities":["s11","s221"]}},"defeatedTeam":{"totalScore":196,"player1":{"pokemon":"clefable","battleItem":"shedinjadoll","playerName":"BuffMewッ","playerScore":19,"kills":1,"assists":10,"interrupts":0,"damageDone":17037,"damageTaken":101897,"damageHealed":86889,"abilities":["s11","s21"]},"player2":{"pokemon":"inteleon","battleItem":"ejectbutton","playerName":"GRN・Leone","playerScore":0,"kills":1,"assists":3,"interrupts":0,"damageDone":28443,"damageTaken":27526,"damageHealed":4167,"abilities":["s11","s21"]},"player3":{"pokemon":"espeon","battleItem":"xspeed","playerName":"Iguzeda","playerScore":74,"kills":5,"assists":7,"interrupts":0,"damageDone":57978,"damageTaken":55881,"damageHealed":2860,"abilities":["s12","s21"]},"player4":{"pokemon":"suicune","battleItem":"ejectbutton","playerName":"NamiSeraphin","playerScore":39,"kills":8,"assists":11,"interrupts":1,"damageDone":63796,"damageTaken":34205,"damageHealed":1937,"abilities":["s11","s21"]},"player5":{"pokemon":"armarouge","battleItem":"xspeed","playerName":"TZ・Thirc","playerScore":64,"kills":11,"assists":8,"interrupts":0,"damageDone":86155,"damageTaken":64770,"damageHealed":6873,"abilities":["s11","s22"]}}},{"matchDate":"18-06-2025 09:51","matchType":"Solo Q.","winnerTeam":{"totalScore":930,"player1":{"pokemon":"pikachu","battleItem":"xattack","playerName":"Optimistman","playerScore":186,"kills":19,"assists":14,"interrupts":0,"damageDone":112666,"damageTaken":51970,"damageHealed":12613,"abilities":["s12","u12"]},"player2":{"pokemon":"inteleon","battleItem":"ejectbutton","playerName":"GRN・Leone","playerScore":145,"kills":6,"assists":8,"interrupts":6,"damageDone":67817,"damageTaken":18774,"damageHealed":6574,"abilities":["s11","s21"]},"player3":{"pokemon":"clefable","battleItem":"gear","playerName":"DaHonored1","playerScore":140,"kills":2,"assists":24,"interrupts":0,"damageDone":18606,"damageTaken":50941,"damageHealed":120865,"abilities":["s11","s22"]},"player4":{"pokemon":"snorlax","battleItem":"xspeed","playerName":"OG*ßrain","playerScore":173,"kills":5,"assists":22,"interrupts":0,"damageDone":37714,"damageTaken":77185,"damageHealed":16280,"abilities":["s12","s22"]},"player5":{"pokemon":"gengar","battleItem":"ejectbutton","playerName":"Twoofakind","playerScore":250,"kills":16,"assists":14,"interrupts":0,"damageDone":100910,"damageTaken":40286,"damageHealed":19798,"abilities":["s21","s11"]}},"defeatedTeam":{"totalScore":182,"player1":{"pokemon":"urshifu","battleItem":"controller","playerName":"nexlevelnex","playerScore":0,"kills":0,"assists":2,"interrupts":2,"damageDone":25225,"damageTaken":68378,"damageHealed":1031,"abilities":["s11","s21"]},"player2":{"pokemon":"venusaur","battleItem":"purify","playerName":"Elanthidr","playerScore":22,"kills":2,"assists":2,"interrupts":0,"damageDone":57351,"damageTaken":63012,"damageHealed":10006,"abilities":["s12","u12"]},"player3":{"pokemon":"greninja","battleItem":"xattack","playerName":"Livinloot","playerScore":0,"kills":3,"assists":0,"interrupts":3,"damageDone":90535,"damageTaken":56148,"damageHealed":11837,"abilities":["s11","s21"]},"player4":{"pokemon":"scizor","battleItem":"xspeed","playerName":"MallyD","playerScore":114,"kills":0,"assists":2,"interrupts":0,"damageDone":29623,"damageTaken":54397,"damageHealed":12138,"abilities":["scythers121","s22"]},"player5":{"pokemon":"wigglytuff","battleItem":"potion","playerName":"duxquack","playerScore":46,"kills":2,"assists":2,"interrupts":2,"damageDone":36422,"damageTaken":95778,"damageHealed":13351,"abilities":["s11","s22"]}}}]